README.txt
setup.py
myorg/__init__.py
myorg.mypackage.egg-info/PKG-INFO
myorg.mypackage.egg-info/SOURCES.txt
myorg.mypackage.egg-info/dependency_links.txt
myorg.mypackage.egg-info/entry_points.txt
myorg.mypackage.egg-info/namespace_packages.txt
myorg.mypackage.egg-info/not-zip-safe
myorg.mypackage.egg-info/paster_plugins.txt
myorg.mypackage.egg-info/requires.txt
myorg.mypackage.egg-info/top_level.txt
myorg/mypackage/__init__.py
myorg/mypackage/tests.py