Metadata-Version: 1.0
Name: myorg.mypackage
Version: 1.0
Summary: ameen test
Home-page: http://svn.plone.org/svn/collective/
Author: UNKNOWN
Author-email: UNKNOWN
License: GPL
Platform: UNKNOWN
Classifier: Framework :: Plone
Classifier: Programming Language :: Python
